luwak/__init__.py
luwak-0.0.1.dist-info/METADATA
luwak-0.0.1.dist-info/WHEEL
luwak-0.0.1.dist-info/RECORD
